tania/__init__.py
tania/main.py
tania-1.0.2.dist-info/LICENSE
tania-1.0.2.dist-info/METADATA
tania-1.0.2.dist-info/WHEEL
tania-1.0.2.dist-info/entry_points.txt
tania-1.0.2.dist-info/top_level.txt
tania-1.0.2.dist-info/RECORD
