Metadata-Version: 2.1
Name: tania
Version: 1.0.2
Summary: A greedy processes sniper
Home-page: https://github.com/bzizou/tania
Author: Bruno Bzeznik
Author-email: Bruno.Bzeznik@univ-grenoble-alpes.fr
License: GNU GPL v3
Classifier: Development Status :: 5 - Production/Stable
Classifier: Operating System :: OS Independent
Classifier: Intended Audience :: Developers
Classifier: Programming Language :: Python
Classifier: Programming Language :: Python :: 3
Classifier: License :: OSI Approved :: GNU General Public License v2 or later (GPLv2+)
Classifier: Topic :: Software Development :: Libraries :: Python Modules
Classifier: Topic :: System :: Systems Administration
Classifier: Topic :: System :: Monitoring
Classifier: Topic :: Utilities
Requires-Python: >=3.5
License-File: LICENSE
Requires-Dist: configparser
Requires-Dist: pathlib
Requires-Dist: filelock
